fds/__init__.py
fds/sdk/__init__.py
fds/sdk/ProcuretoPayProvisioning/__init__.py
fds/sdk/ProcuretoPayProvisioning/api_client.py
fds/sdk/ProcuretoPayProvisioning/configuration.py
fds/sdk/ProcuretoPayProvisioning/exceptions.py
fds/sdk/ProcuretoPayProvisioning/model_utils.py
fds/sdk/ProcuretoPayProvisioning/rest.py
fds/sdk/ProcuretoPayProvisioning/api/__init__.py
fds/sdk/ProcuretoPayProvisioning/api/entitlement_management_api.py
fds/sdk/ProcuretoPayProvisioning/api/order_status_api.py
fds/sdk/ProcuretoPayProvisioning/api/user_management_api.py
fds/sdk/ProcuretoPayProvisioning/apis/__init__.py
fds/sdk/ProcuretoPayProvisioning/model/__init__.py
fds/sdk/ProcuretoPayProvisioning/model/cancel_individual.py
fds/sdk/ProcuretoPayProvisioning/model/create_individual.py
fds/sdk/ProcuretoPayProvisioning/model/get_individual.py
fds/sdk/ProcuretoPayProvisioning/model/inline_response202.py
fds/sdk/ProcuretoPayProvisioning/model/list_individuals.py
fds/sdk/ProcuretoPayProvisioning/model/manage_product_ids.py
fds/sdk/ProcuretoPayProvisioning/model/modify_individual.py
fds/sdk/ProcuretoPayProvisioning/model/transaction_status.py
fds/sdk/ProcuretoPayProvisioning/models/__init__.py
fds.sdk.ProcuretoPayProvisioning-0.9.1.dist-info/LICENSE
fds.sdk.ProcuretoPayProvisioning-0.9.1.dist-info/METADATA
fds.sdk.ProcuretoPayProvisioning-0.9.1.dist-info/WHEEL
fds.sdk.ProcuretoPayProvisioning-0.9.1.dist-info/top_level.txt
fds.sdk.ProcuretoPayProvisioning-0.9.1.dist-info/RECORD
