Metadata-Version: 2.1
Name: fds.sdk.ProcuretoPayProvisioning
Version: 0.9.1
Summary: Procure to Pay: Provisioning client library for Python
Home-page: https://github.com/FactSet/enterprise-sdk/tree/main/code/python/ProcuretoPayProvisioning/v1
Author: FactSet Research Systems
License: Apache-2.0
Keywords: FactSet,API,SDK
Platform: UNKNOWN
Requires-Python: >=3.6
License-File: LICENSE
Requires-Dist: urllib3 (>=1.25.3)
Requires-Dist: python-dateutil
Requires-Dist: fds.sdk.utils (>=0.10.0)
